setup.cfg
setup.py
pytlspsk/__init__.py
pytlspsk/ssl_psk.c
pytlspsk/ssl_psk.py
pytlspsk.egg-info/PKG-INFO
pytlspsk.egg-info/SOURCES.txt
pytlspsk.egg-info/dependency_links.txt
pytlspsk.egg-info/top_level.txt
test/test.py