Metadata-Version: 1.1
Name: pytlspsk
Version: 0.3
Summary: TLS-PSK wrapper for Socket
Home-page: https://github.com/jigneshvasoya/pytlspsk
Author: Jignesh Vasoya
Author-email: jigneshvasoya@gmail.com
License: UNKNOWN
Download-URL: https://github.com/jigneshvasoya/pytlspsk/tarball/0.3
Keywords: OpenSSL,TLS-PSK,tlspsk,security,ssl socket
Platform: UNKNOWN
Classifier: Development Status :: 2 - Pre-Alpha
Classifier: Intended Audience :: Developers
Classifier: License :: OSI Approved :: MIT License
Classifier: Programming Language :: Python
Classifier: Programming Language :: C
